[{"__symbolic":"module","version":3,"metadata":{"LayerData":{"__symbolic":"class","members":{"__ctor__":[{"__symbolic":"constructor","parameters":[{"__symbolic":"reference","name":"Object"},{"__symbolic":"reference","name":"any"}]}]}},"AcLayer2Directive":{"__symbolic":"class","decorators":[{"__symbolic":"call","expression":{"__symbolic":"reference","module":"@angular/core","name":"Directive"},"arguments":[{"selector":"[acLayer2]"}]}],"members":{"acLayer2Of":[{"__symbolic":"property","decorators":[{"__symbolic":"call","expression":{"__symbolic":"reference","module":"@angular/core","name":"Input"}}]}],"__ctor__":[{"__symbolic":"constructor","parameters":[{"__symbolic":"reference","module":"@angular/core","name":"TemplateRef","arguments":[{"__symbolic":"reference","name":"any"}]},{"__symbolic":"reference","module":"@angular/core","name":"ViewContainerRef"},{"__symbolic":"reference","module":"@angular/core","name":"ChangeDetectorRef"},{"__symbolic":"reference","module":"../services/layer-service/layer-service.service","name":"LayerService"}]}]}}}},{"__symbolic":"module","version":1,"metadata":{"LayerData":{"__symbolic":"class","members":{"__ctor__":[{"__symbolic":"constructor","parameters":[{"__symbolic":"reference","name":"Object"},{"__symbolic":"reference","name":"any"}]}]}},"AcLayer2Directive":{"__symbolic":"class","decorators":[{"__symbolic":"call","expression":{"__symbolic":"reference","module":"@angular/core","name":"Directive"},"arguments":[{"selector":"[acLayer2]"}]}],"members":{"acLayer2Of":[{"__symbolic":"property","decorators":[{"__symbolic":"call","expression":{"__symbolic":"reference","module":"@angular/core","name":"Input"}}]}],"__ctor__":[{"__symbolic":"constructor","parameters":[{"__symbolic":"reference","module":"@angular/core","name":"TemplateRef","arguments":[{"__symbolic":"reference","name":"any"}]},{"__symbolic":"reference","module":"@angular/core","name":"ViewContainerRef"},{"__symbolic":"reference","module":"@angular/core","name":"ChangeDetectorRef"},{"__symbolic":"reference","module":"../services/layer-service/layer-service.service","name":"LayerService"}]}]}}}}]